objectcrawler/__init__.py
objectcrawler/crawler.py
objectcrawler/entity.py
objectcrawler/get_assignment.py
objectcrawler-0.0.2.dist-info/LICENSE
objectcrawler-0.0.2.dist-info/METADATA
objectcrawler-0.0.2.dist-info/WHEEL
objectcrawler-0.0.2.dist-info/top_level.txt
objectcrawler-0.0.2.dist-info/RECORD
