Metadata-Version: 2.1
Name: objectcrawler
Version: 0.0.2
Summary: simple object crawling debug tool
Author-email: Louis Beal <louis.j.beal@gmail.com>
Project-URL: Homepage, https://github.com/ljbeal/ObjectCrawler
Project-URL: Documentation, https://github.com/ljbeal/ObjectCrawler
Project-URL: Repository, https://github.com/ljbeal/ObjectCrawler
Project-URL: Issues, https://github.com/ljbeal/ObjectCrawler/issues
Keywords: debug,inspect,inspection
Classifier: Topic :: Software Development :: Debuggers
Classifier: License :: OSI Approved :: MIT License
Classifier: Programming Language :: Python :: 3.9
Classifier: Programming Language :: Python :: 3.10
Classifier: Programming Language :: Python :: 3.11
Classifier: Programming Language :: Python :: 3.12
Classifier: Operating System :: OS Independent
Requires-Python: >=3.7
License-File: LICENSE
Provides-Extra: dev
Requires-Dist: pylint ; extra == 'dev'
Requires-Dist: flake8 ; extra == 'dev'
Requires-Dist: black ; extra == 'dev'
